Workbook

Sheet WACC
B2: Weighted Average Cost of Capital
B4: All figures are in INR unless stated otherwise
B6: Peer Comps
G7: Debt / | H7: Debt / | I7: Levered | J7: Unlevered
B8: Name of the Comp | C8: Country | D8: Total Debt | E8: Total Equity | F8: Tax Rate 1 | G8: Equity | H8: Capital | I8: Beta 2 | J8: Beta 3
B10: JSW Steel | C10: India | D10: 98752 | E10: 245902.62 | F10: 0.3 | G10: =D10/E10 -> 0.40158987 | H10: =D10/(D10+E10) -> 0.28652452 | I10: ='peers Levered Beta - regression'!E5 -> 1.1292529 | J10: =I10/(1+(1-F10)*(G10)) -> 0.88146242
B11: Tata Steel | C11: India | D11: 94801.05 | E11: 189712.16 | F11: 0.3 | G11: =D11/E11 -> 0.49970993 | H11: =D11/(D11+E11) -> 0.33320439 | I11: ='peers Levered Beta - regression'!E6 -> 1.3540647 | J11: =I11/(1+(1-F11)*(G11)) -> 1.0031618
B12: Jindal Steel | C12: India | D12: 18406.08 | E12: 91711.02 | F12: 0.3 | G12: =D12/E12 -> 0.20069649 | H12: =D12/(D12+E12) -> 0.16715006 | I12: ='peers Levered Beta - regression'!E7 -> 1.3052257 | J12: =I12/(1+(1-F12)*(G12)) -> 1.1444453
B13: S A I L | C13: India | D13: 36933.94 | E13: 52655.94 | F13: 0.3 | G13: =D13/E13 -> 0.7014202 | H13: =D13/(D13+E13) -> 0.41225571 | I13: ='peers Levered Beta - regression'!E8 -> 1.5705924 | J13: =I13/(1+(1-F13)*(G13)) -> 1.053386
B14: Sarda Energy | C14: India | D14: 2861.05 | E14: 15199.97 | F14: 0.3 | G14: =D14/E14 -> 0.18822735 | H14: =D14/(D14+E14) -> 0.15841021 | I14: ='peers Levered Beta - regression'!E9 -> 1.2320998 | J14: =I14/(1+(1-F14)*(G14)) -> 1.088659
E16: Average | F16: =AVERAGE(F10:F14) -> 0.3 | G16: =AVERAGE(G10:G14) -> 0.39832877 | H16: =AVERAGE(H10:H14) -> 0.27150898 | I16: =AVERAGE(I10:I14) -> 1.3182471 | J16: =AVERAGE(J10:J14) -> 1.0342229
E17: Median | F17: =MEDIAN(F10:F14) -> 0.3 | G17: =MEDIAN(G10:G14) -> 0.40158987 | H17: =MEDIAN(H10:H14) -> 0.28652452 | I17: =MEDIAN(I10:I14) -> 1.3052257 | J17: =MEDIAN(J10:J14) -> 1.053386
B20: Cost of Debt | G20: Cost of Equity
B22: Pre tax cost of Debt | E22: ='WACC input data'!C10+(0.75*'WACC input data'!C11)+'WACC input data'!C12 -> 0.068055 | G22: Risk-Free Rate | J22: ='WACC input data'!C10 -> 0.04008
B23: tax Rate | E23: =F17 -> 0.3 | G23: Market Risk Premium | J23: ='WACC input data'!C7 -> 0.0726
B24: Post Tax cost of Debt | E24: =E22*(1-E23) -> 0.0476385 | G24: Levered Beta 4 | J24: =J32 -> 1.3282043
G25: cost of equity | J25: =J22+(J24*J23) -> 0.13650763
B27: Capital structure | G27: Levered Beta
D28: Current | E28: Target
B29: Total Debt | C29: =D10 -> 98752 | D29: =C29/C31 -> 0.28652452 | E29: =H16 -> 0.27150898 | G29: comps Median Unlevered Beta | J29: =J17 -> 1.053386
B30: Market Capitalization | C30: =E10 -> 245902.62 | D30: =C30/C31 -> 0.71347548 | E30: =E31-E29 -> 0.72849102 | G30: Target Debt/Equity | J30: =E33 -> 0.37270052
B31: Total Capital | C31: =C29+C30 -> 344654.62 | D31: =D29+D30 -> 1 | E31: 1 | G31: Tax rate | J31: =E23 -> 0.3
G32: Levered Beta | J32: =J29*(1+((1-J31)*J30)) -> 1.3282043
B33: Debt / Equity | D33: =D29/D30 -> 0.40158987 | E33: =E29/E30 -> 0.37270052
B35: Capital structure
D36: Total cost | E36: Total Weight
B37: Debt | D37: =E24 -> 0.0476385 | E37: =E29 -> 0.27150898
B38: Equity | D38: =J25 -> 0.13650763 | E38: =E30 -> 0.72849102
A39: x | B39: Weighted average Cost of Capital | E39: =(D37*E37)+(D38*E38) -> 0.11237886
B42: Notes
B43: 1. Tax Rate Considered as Marginal Tax Rate of the country
B44: 2. Levered Beta is based on 3 year weekly data
B45: 3. Unlevered Beta = Levered Beta / (1+ (1- Tax rate ) * ( debt / Equity ))
B46: 4. Levered Beta = Unlevered Beta * (1+ (1- Tax rate ) * ( debt / Equity ))

Sheet peers Levered Beta - regression
B1: Peers Levered Beta - Regression | F1: Weekly Three Year data used for Regression
B4: Peer Name | C4: Total Debt | D4: Total Equity | E4: Levered Beta
B5: JSW Steel | C5: 98752 | D5: 245902.62 | E5: =SLOPE($G$14:$G$193,$E$14:$E$193) -> 1.1292529
B6: Tata Steel | C6: 94801.05 | D6: 189712.16 | E6: =SLOPE(I14:I193,$E$14:$E$193) -> 1.3540647
B7: Jindal Steel | C7: 18406.08 | D7: 91711.02 | E7: =SLOPE($K$14:$K$193,$E$14:$E$193) -> 1.3052257
B8: S A I L | C8: 36933.94 | D8: 52655.94 | E8: =SLOPE($M$14:$M$193,$E$14:$E$193) -> 1.5705924
B9: Sarda Energy | C9: 2861.05 | D9: 15199.97 | E9: =SLOPE($O$14:$O$193,$E$14:$E$193) -> 1.2320998
D11: Nifty | F11: JSTL | H11: TISC | J11: JNSP | L11: SAIL | N11: SAEM
B12: Date | D12: Price | E12: Growth | F12: Price | G12: Growth | H12: Price | I12: Growth | J12: Price | K12: Growth | L12: Price | M12: Growth | N12: Price | O12: Growth
B13: 15-06-2025 | D13: 25112.4 | F13: 1005.55 | H13: 151.97 | J13: 899.05 | L13: 127.48 | N13: 431.35
B14: 45875 | D14: 24718.6 | E14: =D14/D13-1 -> -0.015681496 | F14: 987.25 | G14: =F14/F13-1 -> -0.018198996 | H14: 152.13 | I14: =H14/H13-1 -> 0.0010528394 | J14: 920.75 | K14: =J14/J13-1 -> 0.024136589 | L14: 129.35 | M14: =L14/L13-1 -> 0.014668968 | N14: 448.95 | O14: =N14/N13-1 -> 0.040802133
B15: 45663 | D15: 25003.05 | E15: =D15/D14-1 -> 0.011507529 | F15: 1004.9 | G15: =F15/F14-1 -> 0.017877944 | H15: 157.49 | I15: =H15/H14-1 -> 0.035233024 | J15: 962.75 | K15: =J15/J14-1 -> 0.045614988 | L15: 135.04 | M15: =L15/L14-1 -> 0.043989177 | N15: 435.95 | O15: =N15/N14-1 -> -0.028956454
B16: 25-05-2025 | D16: 24750.7 | E16: =D16/D15-1 -> -0.010092769 | F16: 993.5 | G16: =F16/F15-1 -> -0.011344412 | H16: 161.02 | I16: =H16/H15-1 -> 0.022414122 | J16: 948.9 | K16: =J16/J15-1 -> -0.014385874 | L16: 129.18 | M16: =L16/L15-1 -> -0.04339455 | N16: 437.1 | O16: =N16/N15-1 -> 0.0026379172
B17: 18-05-2025 | D17: 24853.15 | E17: =D17/D16-1 -> 0.0041392769 | F17: 1008.5 | G17: =F17/F16-1 -> 0.015098138 | H17: 162.97 | I17: =H17/H16-1 -> 0.012110297 | J17: 953.4 | K17: =J17/J16-1 -> 0.0047423332 | L17: 125.92 | M17: =L17/L16-1 -> -0.025236105 | N17: 469.4 | O17: =N17/N16-1 -> 0.073896134
B18: 45966 | D18: 25019.8 | E18: =D18/D17-1 -> 0.0067053874 | F18: 1021.8 | G18: =F18/F17-1 -> 0.013187903 | H18: 157.55 | I18: =H18/H17-1 -> -0.033257655 | J18: 981.6 | K18: =J18/J17-1 -> 0.029578351 | L18: 122.48 | M18: =L18/L17-1 -> -0.027318933 | N18: 454.75 | O18: =N18/N17-1 -> -0.031210055
B19: 45752 | D19: 24008 | E19: =D19/D18-1 -> -0.040439972 | F19: 957 | G19: =F19/F18-1 -> -0.063417499 | H19: 142.78 | I19: =H19/H18-1 -> -0.093748017 | J19: 855.35 | K19: =J19/J18-1 -> -0.12861654 | L19: 109.01 | M19: =L19/L18-1 -> -0.10997714 | N19: 421.4 | O19: =N19/N18-1 -> -0.073336998
B20: 27-04-2025 | D20: 24346.7 | E20: =D20/D19-1 -> 0.014107797 | F20: 973.2 | G20: =F20/F19-1 -> 0.0169279 | H20: 141.18 | I20: =H20/H19-1 -> -0.011206051 | J20: 897.75 | K20: =J20/J19-1 -> 0.049570351 | L20: 113.22 | M20: =L20/L19-1 -> 0.03862031 | N20: 442.2 | O20: =N20/N19-1 -> 0.049359279
B21: 20-04-2025 | D21: 24039.35 | E21: =D21/D20-1 -> -0.012623887 | F21: 1028.4 | G21: =F21/F20-1 -> 0.056720099 | H21: 138.85 | I21: =H21/H20-1 -> -0.016503754 | J21: 891.8 | K21: =J21/J20-1 -> -0.0066276803 | L21: 114.81 | M21: =L21/L20-1 -> 0.014043455 | N21: 477.25 | O21: =N21/N20-1 -> 0.079262777
B22: 13-04-2025 | D22: 23851.65 | E22: =D22/D21-1 -> -0.0078080314 | F22: 1007.2 | G22: =F22/F21-1 -> -0.020614547 | H22: 137.14 | I22: =H22/H21-1 -> -0.012315448 | J22: 881.7 | K22: =J22/J21-1 -> -0.011325409 | L22: 113.96 | M22: =L22/L21-1 -> -0.0074035363 | N22: 479.1 | O22: =N22/N21-1 -> 0.0038763751
B23: 45812 | D23: 22828.55 | E23: =D23/D22-1 -> -0.042894307 | F23: 990.25 | G23: =F23/F22-1 -> -0.016828832 | H23: 133.42 | I23: =H23/H22-1 -> -0.027125565 | J23: 805.65 | K23: =J23/J22-1 -> -0.086253828 | L23: 108.34 | M23: =L23/L22-1 -> -0.049315549 | N23: 467.65 | O23: =N23/N22-1 -> -0.023898977
B24: 30-03-2025 | D24: 22904.45 | E24: =D24/D23-1 -> 0.0033247841 | F24: 1005.75 | G24: =F24/F23-1 -> 0.015652613 | H24: 140.39 | I24: =H24/H23-1 -> 0.052241043 | J24: 850.1 | K24: =J24/J23-1 -> 0.055172842 | L24: 112.6 | M24: =L24/L23-1 -> 0.039320657 | N24: 495.75 | O24: =N24/N23-1 -> 0.060087672
B25: 23-03-2025 | D25: 23519.35 | E25: =D25/D24-1 -> 0.026846312 | F25: 1063.2 | G25: =F25/F24-1 -> 0.057121551 | H25: 154.24 | I25: =H25/H24-1 -> 0.09865375 | J25: 912.3 | K25: =J25/J24-1 -> 0.073167863 | L25: 115.18 | M25: =L25/L24-1 -> 0.022912966 | N25: 513.9 | O25: =N25/N24-1 -> 0.036611195
B26: 16-03-2025 | D26: 23350.4 | E26: =D26/D25-1 -> -0.0071834468 | F26: 1058.7 | G26: =F26/F25-1 -> -0.0042325056 | H26: 157.28 | I26: =H26/H25-1 -> 0.019709544 | J26: 914.3 | K26: =J26/J25-1 -> 0.0021922613 | L26: 115.3 | M26: =L26/L25-1 -> 0.0010418475 | N26: 545.55 | O26: =N26/N25-1 -> 0.061587858
B27: 45903 | D27: 22397.2 | E27: =D27/D26-1 -> -0.040821571 | F27: 1001.2 | G27: =F27/F26-1 -> -0.054311892 | H27: 150.88 | I27: =H27/H26-1 -> -0.04069176 | J27: 889.7 | K27: =J27/J26-1 -> -0.02690583 | L27: 105.89 | M27: =L27/L26-1 -> -0.081613183 | N27: 541.05 | O27: =N27/N26-1 -> -0.0082485565
B28: 45691 | D28: 22552.5 | E28: =D28/D27-1 -> 0.0069339025 | F28: 1011.15 | G28: =F28/F27-1 -> 0.0099380743 | H28: 151.56 | I28: =H28/H27-1 -> 0.0045068929 | J28: 908.95 | K28: =J28/J27-1 -> 0.021636507 | L28: 110.91 | M28: =L28/L27-1 -> 0.047407687 | N28: 471.05 | O28: =N28/N27-1 -> -0.12937806
B29: 23-02-2025 | D29: 22124.7 | E29: =D29/D28-1 -> -0.018969072 | F29: 950.7 | G29: =F29/F28-1 -> -0.059783415 | H29: 137.2 | I29: =H29/H28-1 -> -0.094747955 | J29: 856.15 | K29: =J29/J28-1 -> -0.058089004 | L29: 105.02 | M29: =L29/L28-1 -> -0.053106122 | N29: 453.55 | O29: =N29/N28-1 -> -0.037151046
B30: 16-02-2025 | D30: 22795.9 | E30: =D30/D29-1 -> 0.030337135 | F30: 981.9 | G30: =F30/F29-1 -> 0.032817924 | H30: 140.76 | I30: =H30/H29-1 -> 0.025947522 | J30: 880.35 | K30: =J30/J29-1 -> 0.028266075 | L30: 112.76 | M30: =L30/L29-1 -> 0.073700248 | N30: 489.65 | O30: =N30/N29-1 -> 0.079594312
B31: 45902 | D31: 22929.25 | E31: =D31/D30-1 -> 0.0058497361 | F31: 964.6 | G31: =F31/F30-1 -> -0.017618902 | H31: 134.47 | I31: =H31/H30-1 -> -0.04468599 | J31: 833.3 | K31: =J31/J30-1 -> -0.053444653 | L31: 105.71 | M31: =L31/L30-1 -> -0.062522171 | N31: 458.05 | O31: =N31/N30-1 -> -0.064535893
B32: 45690 | D32: 23559.95 | E32: =D32/D31-1 -> 0.027506351 | F32: 980.75 | G32: =F32/F31-1 -> 0.016742691 | H32: 138.31 | I32: =H32/H31-1 -> 0.028556555 | J32: 844.55 | K32: =J32/J31-1 -> 0.01350054 | L32: 110.32 | M32: =L32/L31-1 -> 0.043609876 | N32: 466.25 | O32: =N32/N31-1 -> 0.017901976
B33: 26-01-2025 | D33: 23508.4 | E33: =D33/D32-1 -> -0.0021880352 | F33: 945 | G33: =F33/F32-1 -> -0.036451695 | H33: 134.62 | I33: =H33/H32-1 -> -0.026679199 | J33: 791.55 | K33: =J33/J32-1 -> -0.062755313 | L33: 107.43 | M33: =L33/L32-1 -> -0.026196519 | N33: 473.2 | O33: =N33/N32-1 -> 0.014906166
B34: 19-01-2025 | D34: 23092.2 | E34: =D34/D33-1 -> -0.01770431 | F34: 932.45 | G34: =F34/F33-1 -> -0.013280423 | H34: 129.74 | I34: =H34/H33-1 -> -0.036250186 | J34: 882.8 | K34: =J34/J33-1 -> 0.11528015 | L34: 108.17 | M34: =L34/L33-1 -> 0.0068882063 | N34: 431.2 | O34: =N34/N33-1 -> -0.088757396
B35: 45992 | D35: 23203.2 | E35: =D35/D34-1 -> 0.0048068179 | F35: 908.6 | G35: =F35/F34-1 -> -0.025577779 | H35: 130.28 | I35: =H35/H34-1 -> 0.0041621705 | J35: 924.65 | K35: =J35/J34-1 -> 0.047405981 | L35: 108.82 | M35: =L35/L34-1 -> 0.0060090598 | N35: 426.85 | O35: =N35/N34-1 -> -0.010088126
B36: 45778 | D36: 23431.5 | E36: =D36/D35-1 -> 0.0098391601 | F36: 900.1 | G36: =F36/F35-1 -> -0.0093550517 | H36: 127.43 | I36: =H36/H35-1 -> -0.021875959 | J36: 917.7 | K36: =J36/J35-1 -> -0.0075163575 | L36: 106.03 | M36: =L36/L35-1 -> -0.025638669 | N36: 470.65 | O36: =N36/N35-1 -> 0.10261216
B37: 29-12-2024 | D37: 24004.75 | E37: =D37/D36-1 -> 0.02446493 | F37: 915.05 | G37: =F37/F36-1 -> 0.016609266 | H37: 138.36 | I37: =H37/H36-1 -> 0.085772581 | J37: 957.85 | K37: =J37/J36-1 -> 0.043750681 | L37: 114.17 | M37: =L37/L36-1 -> 0.076770725 | N37: 481.15 | O37: =N37/N36-1 -> 0.022309572
B38: 22-12-2024 | D38: 23813.4 | E38: =D38/D37-1 -> -0.007971339 | F38: 913.3 | G38: =F38/F37-1 -> -0.0019124638 | H38: 138.91 | I38: =H38/H37-1 -> 0.0039751373 | J38: 923.55 | K38: =J38/J37-1 -> -0.035809365 | L38: 115.53 | M38: =L38/L37-1 -> 0.011912061 | N38: 478.3 | O38: =N38/N37-1 -> -0.0059233087
B39: 15-12-2024 | D39: 23587.5 | E39: =D39/D38-1 -> -0.0094862556 | F39: 917.35 | G39: =F39/F38-1 -> 0.0044344684 | H39: 140.68 | I39: =H39/H38-1 -> 0.012742063 | J39: 908.05 | K39: =J39/J38-1 -> -0.016783065 | L39: 116.1 | M39: =L39/L38-1 -> 0.0049337834 | N39: 469.6 | O39: =N39/N38-1 -> -0.018189421
B40: 45516 | D40: 24768.3 | E40: =D40/D39-1 -> 0.050060413 | F40: 999.85 | G40: =F40/F39-1 -> 0.089932959 | H40: 148.95 | I40: =H40/H39-1 -> 0.058785897 | J40: 998.75 | K40: =J40/J39-1 -> 0.099884368 | L40: 124.76 | M40: =L40/L39-1 -> 0.07459087 | N40: 478.15 | O40: =N40/N39-1 -> 0.018206985
B41: 45303 | D41: 24677.8 | E41: =D41/D40-1 -> -0.003653864 | F41: 1003.8 | G41: =F41/F40-1 -> 0.0039505926 | H41: 148.29 | I41: =H41/H40-1 -> -0.0044310171 | J41: 949.1 | K41: =J41/J40-1 -> -0.04971214 | L41: 123.89 | M41: =L41/L40-1 -> -0.0069733889 | N41: 472.5 | O41: =N41/N40-1 -> -0.011816376
B42: 24-11-2024 | D42: 24131.1 | E42: =D42/D41-1 -> -0.022153514 | F42: 966 | G42: =F42/F41-1 -> -0.037656904 | H42: 144.54 | I42: =H42/H41-1 -> -0.025288286 | J42: 906.45 | K42: =J42/J41-1 -> -0.044937309 | L42: 117.11 | M42: =L42/L41-1 -> -0.054725967 | N42: 447 | O42: =N42/N41-1 -> -0.053968254
B43: 17-11-2024 | D43: 23907.25 | E43: =D43/D42-1 -> -0.0092764109 | F43: 977.35 | G43: =F43/F42-1 -> 0.011749482 | H43: 142.78 | I43: =H43/H42-1 -> -0.01217656 | J43: 878.95 | K43: =J43/J42-1 -> -0.030338132 | L43: 112.83 | M43: =L43/L42-1 -> -0.036546836 | N43: 414 | O43: =N43/N42-1 -> -0.073825503
B44: 45576 | D44: 23532.7 | E44: =D44/D43-1 -> -0.015666796 | F44: 939.05 | G44: =F44/F43-1 -> -0.039187599 | H44: 137.98 | I44: =H44/H43-1 -> -0.033618154 | J44: 877.4 | K44: =J44/J43-1 -> -0.0017634678 | L44: 111.84 | M44: =L44/L43-1 -> -0.0087742622 | N44: 428.3 | O44: =N44/N43-1 -> 0.034541063
B45: 45362 | D45: 24148.2 | E45: =D45/D44-1 -> 0.026155095 | F45: 996.4 | G45: =F45/F44-1 -> 0.06107236 | H45: 147.57 | I45: =H45/H44-1 -> 0.069502826 | J45: 928.05 | K45: =J45/J44-1 -> 0.057727376 | L45: 118.21 | M45: =L45/L44-1 -> 0.056956366 | N45: 462.4 | O45: =N45/N44-1 -> 0.079617091
B46: 27-10-2024 | D46: 24304.35 | E46: =D46/D45-1 -> 0.0064663205 | F46: 968.3 | G46: =F46/F45-1 -> -0.028201525 | H46: 149.75 | I46: =H46/H45-1 -> 0.01477265 | J46: 929.5 | K46: =J46/J45-1 -> 0.0015624158 | L46: 117.75 | M46: =L46/L45-1 -> -0.0038913797 | N46: 455.45 | O46: =N46/N45-1 -> -0.015030277
B47: 20-10-2024 | D47: 24180.8 | E47: =D47/D46-1 -> -0.0050834521 | F47: 943.85 | G47: =F47/F46-1 -> -0.025250439 | H47: 145.86 | I47: =H47/H46-1 -> -0.025976628 | J47: 899.05 | K47: =J47/J46-1 -> -0.032759548 | L47: 111.48 | M47: =L47/L46-1 -> -0.053248408 | N47: 462.4 | O47: =N47/N46-1 -> 0.015259633
B48: 13-10-2024 | D48: 24854.05 | E48: =D48/D47-1 -> 0.027842338 | F48: 992.6 | G48: =F48/F47-1 -> 0.051650156 | H48: 155.39 | I48: =H48/H47-1 -> 0.065336624 | J48: 964.5 | K48: =J48/J47-1 -> 0.072799066 | L48: 129.03 | M48: =L48/L47-1 -> 0.15742734 | N48: 506.6 | O48: =N48/N47-1 -> 0.095588235
B49: 45453 | D49: 24964.25 | E49: =D49/D48-1 -> 0.004433885 | F49: 1012.05 | G49: =F49/F48-1 -> 0.019595003 | H49: 160.66 | I49: =H49/H48-1 -> 0.033914666 | J49: 1005.85 | K49: =J49/J48-1 -> 0.042871954 | L49: 134.03 | M49: =L49/L48-1 -> 0.038750678 | N49: 499.5 | O49: =N49/N48-1 -> -0.014015002
B50: 29-09-2024 | D50: 25014.6 | E50: =D50/D49-1 -> 0.0020168841 | F50: 1033.75 | G50: =F50/F49-1 -> 0.021441628 | H50: 166.75 | I50: =H50/H49-1 -> 0.037906137 | J50: 1021.1 | K50: =J50/J49-1 -> 0.015161306 | L50: 139.01 | M50: =L50/L49-1 -> 0.037155861 | N50: 480.2 | O50: =N50/N49-1 -> -0.038638639
B51: 22-09-2024 | D51: 26178.95 | E51: =D51/D50-1 -> 0.046546817 | F51: 1001.55 | G51: =F51/F50-1 -> -0.03114873 | H51: 166.55 | I51: =H51/H50-1 -> -0.0011994003 | J51: 1028.05 | K51: =J51/J50-1 -> 0.0068063853 | L51: 140.54 | M51: =L51/L50-1 -> 0.011006402 | N51: 439.2 | O51: =N51/N50-1 -> -0.085381091
B52: 15-09-2024 | D52: 25790.95 | E52: =D52/D51-1 -> -0.014821068 | F52: 981.55 | G52: =F52/F51-1 -> -0.019969048 | H52: 152.02 | I52: =H52/H51-1 -> -0.087241069 | J52: 1009.4 | K52: =J52/J51-1 -> -0.018141141 | L52: 126.28 | M52: =L52/L51-1 -> -0.10146577 | N52: 418.2 | O52: =N52/N51-1 -> -0.047814208
B53: 45513 | D53: 25356.5 | E53: =D53/D52-1 -> -0.016845056 | F53: 954.55 | G53: =F53/F52-1 -> -0.027507514 | H53: 153.49 | I53: =H53/H52-1 -> 0.0096697803 | J53: 1031.1 | K53: =J53/J52-1 -> 0.02149792 | L53: 132.2 | M53: =L53/L52-1 -> 0.046879949 | N53: 382.6 | O53: =N53/N52-1 -> -0.085126734
B54: 45300 | D54: 24852.15 | E54: =D54/D53-1 -> -0.019890363 | F54: 932.8 | G54: =F54/F53-1 -> -0.022785606 | H54: 151.22 | I54: =H54/H53-1 -> -0.014789237 | J54: 953.95 | K54: =J54/J53-1 -> -0.074823005 | L54: 129.38 | M54: =L54/L53-1 -> -0.021331316 | N54: 355.85 | O54: =N54/N53-1 -> -0.069916362
B55: 25-08-2024 | D55: 25235.9 | E55: =D55/D54-1 -> 0.01544132 | F55: 941.1 | G55: =F55/F54-1 -> 0.0088979417 | H55: 152.76 | I55: =H55/H54-1 -> 0.010183838 | J55: 970.4 | K55: =J55/J54-1 -> 0.01724409 | L55: 133.69 | M55: =L55/L54-1 -> 0.033312722 | N55: 351.65 | O55: =N55/N54-1 -> -0.011802726
B56: 18-08-2024 | D56: 24823.15 | E56: =D56/D55-1 -> -0.016355668 | F56: 941.05 | G56: =F56/F55-1 -> -5.3129317e-05 | H56: 154.2 | I56: =H56/H55-1 -> 0.0094265515 | J56: 959.85 | K56: =J56/J55-1 -> -0.010871805 | L56: 131.79 | M56: =L56/L55-1 -> -0.014211983 | N56: 347.2 | O56: =N56/N55-1 -> -0.012654628
B57: 45604 | D57: 24541.15 | E57: =D57/D56-1 -> -0.011360363 | F57: 908.45 | G57: =F57/F56-1 -> -0.034642155 | H57: 149.52 | I57: =H57/H56-1 -> -0.030350195 | J57: 934.5 | K57: =J57/J56-1 -> -0.026410377 | L57: 128.28 | M57: =L57/L56-1 -> -0.02663328 | N57: 337.15 | O57: =N57/N56-1 -> -0.028945853
B58: 45390 | D58: 24367.5 | E58: =D58/D57-1 -> -0.0070758705 | F58: 905.1 | G58: =F58/F57-1 -> -0.0036875998 | H58: 151.81 | I58: =H58/H57-1 -> 0.015315677 | J58: 916.2 | K58: =J58/J57-1 -> -0.019582665 | L58: 129.35 | M58: =L58/L57-1 -> 0.0083411288 | N58: 277.35 | O58: =N58/N57-1 -> -0.17736912
B59: 28-07-2024 | D59: 24717.7 | E59: =D59/D58-1 -> 0.014371602 | F59: 899.55 | G59: =F59/F58-1 -> -0.0061319191 | H59: 158.22 | I59: =H59/H58-1 -> 0.042223832 | J59: 956.75 | K59: =J59/J58-1 -> 0.044258895 | L59: 146.23 | M59: =L59/L58-1 -> 0.13049865 | N59: 259.4 | O59: =N59/N58-1 -> -0.064719668
B60: 21-07-2024 | D60: 24834.85 | E60: =D60/D59-1 -> 0.0047395186 | F60: 900.55 | G60: =F60/F59-1 -> 0.0011116669 | H60: 162.55 | I60: =H60/H59-1 -> 0.027366957 | J60: 972.35 | K60: =J60/J59-1 -> 0.0163052 | L60: 147.39 | M60: =L60/L59-1 -> 0.0079327087 | N60: 275.05 | O60: =N60/N59-1 -> 0.060331534
B61: 14-07-2024 | D61: 24530.9 | E61: =D61/D60-1 -> -0.01223885 | F61: 889.45 | G61: =F61/F60-1 -> -0.012325801 | H61: 157.77 | I61: =H61/H60-1 -> -0.029406337 | J61: 946.35 | K61: =J61/J60-1 -> -0.026739343 | L61: 141.82 | M61: =L61/L60-1 -> -0.037790895 | N61: 271.47 | O61: =N61/N60-1 -> -0.013015815
B62: 45480 | D62: 24502.15 | E62: =D62/D61-1 -> -0.0011719912 | F62: 934.4 | G62: =F62/F61-1 -> 0.050536849 | H62: 168.69 | I62: =H62/H61-1 -> 0.06921468 | J62: 1013.9 | K62: =J62/J61-1 -> 0.071379511 | L62: 150.42 | M62: =L62/L61-1 -> 0.060640248 | N62: 274.01 | O62: =N62/N61-1 -> 0.0093564666
B63: 30-06-2024 | D63: 24323.85 | E63: =D63/D62-1 -> -0.0072769124 | F63: 954.05 | G63: =F63/F62-1 -> 0.021029538 | H63: 174.71 | I63: =H63/H62-1 -> 0.035686763 | J63: 1050.5 | K63: =J63/J62-1 -> 0.036098235 | L63: 155.61 | M63: =L63/L62-1 -> 0.034503391 | N63: 245.99 | O63: =N63/N62-1 -> -0.10225904
B64: 23-06-2024 | D64: 24010.6 | E64: =D64/D63-1 -> -0.012878307 | F64: 931.5 | G64: =F64/F63-1 -> -0.023636078 | H64: 174.01 | I64: =H64/H63-1 -> -0.0040066396 | J64: 1044.4 | K64: =J64/J63-1 -> -0.0058067587 | L64: 148.65 | M64: =L64/L63-1 -> -0.044727203 | N64: 232.58 | O64: =N64/N63-1 -> -0.054514411
B65: 16-06-2024 | D65: 23501.1 | E65: =D65/D64-1 -> -0.021219795 | F65: 936.9 | G65: =F65/F64-1 -> 0.0057971014 | H65: 179.94 | I65: =H65/H64-1 -> 0.034078501 | J65: 1077.25 | K65: =J65/J64-1 -> 0.031453466 | L65: 155.44 | M65: =L65/L64-1 -> 0.045677767 | N65: 226.35 | O65: =N65/N64-1 -> -0.026786482
B66: 45541 | D66: 23465.6 | E66: =D66/D65-1 -> -0.0015105676 | F66: 921.15 | G66: =F66/F65-1 -> -0.016810759 | H66: 183.15 | I66: =H66/H65-1 -> 0.01783928 | J66: 1052.45 | K66: =J66/J65-1 -> -0.023021583 | L66: 153.63 | M66: =L66/L65-1 -> -0.011644364 | N66: 236.05 | O66: =N66/N65-1 -> 0.042853987
B67: 45328 | D67: 23290.15 | E67: =D67/D66-1 -> -0.0074769024 | F67: 912.15 | G67: =F67/F66-1 -> -0.0097703957 | H67: 178.9 | I67: =H67/H66-1 -> -0.023205023 | J67: 1026.95 | K67: =J67/J66-1 -> -0.02422918 | L67: 152.75 | M67: =L67/L66-1 -> -0.0057280479 | N67: 220.75 | O67: =N67/N66-1 -> -0.064816776
B68: 26-05-2024 | D68: 22530.7 | E68: =D68/D67-1 -> -0.032608206 | F68: 880.55 | G68: =F68/F67-1 -> -0.034643425 | H68: 167.2 | I68: =H68/H67-1 -> -0.065399665 | J68: 1028.15 | K68: =J68/J67-1 -> 0.0011685087 | L68: 158.5 | M68: =L68/L67-1 -> 0.037643208 | N68: 223.95 | O68: =N68/N67-1 -> 0.014496036
B69: 19-05-2024 | D69: 22957.1 | E69: =D69/D68-1 -> 0.018925289 | F69: 908.65 | G69: =F69/F68-1 -> 0.031911873 | H69: 174.85 | I69: =H69/H68-1 -> 0.045753589 | J69: 1069.2 | K69: =J69/J68-1 -> 0.039926081 | L69: 169.5 | M69: =L69/L68-1 -> 0.069400631 | N69: 264.1 | O69: =N69/N68-1 -> 0.17928109
B70: 45631 | D70: 22466.1 | E70: =D70/D69-1 -> -0.021387719 | F70: 907.45 | G70: =F70/F69-1 -> -0.0013206405 | H70: 167.35 | I70: =H70/H69-1 -> -0.042893909 | J70: 1015.5 | K70: =J70/J69-1 -> -0.050224467 | L70: 166.9 | M70: =L70/L69-1 -> -0.015339233 | N70: 267.15 | O70: =N70/N69-1 -> 0.011548656
B71: 45417 | D71: 22055.2 | E71: =D71/D70-1 -> -0.018289779 | F71: 853.6 | G71: =F71/F70-1 -> -0.059342113 | H71: 162.25 | I71: =H71/H70-1 -> -0.030475052 | J71: 930.55 | K71: =J71/J70-1 -> -0.083653373 | L71: 156.9 | M71: =L71/L70-1 -> -0.059916117 | N71: 268.95 | O71: =N71/N70-1 -> 0.0067377878
B72: 28-04-2024 | D72: 22475.85 | E72: =D72/D71-1 -> 0.0190726 | F72: 874.2 | G72: =F72/F71-1 -> 0.024133083 | H72: 166.5 | I72: =H72/H71-1 -> 0.026194145 | J72: 931.5 | K72: =J72/J71-1 -> 0.0010209016 | L72: 167.95 | M72: =L72/L71-1 -> 0.070427024 | N72: 267.45 | O72: =N72/N71-1 -> -0.0055772448
B73: 21-04-2024 | D73: 22419.95 | E73: =D73/D72-1 -> -0.0024871139 | F73: 887.25 | G73: =F73/F72-1 -> 0.014927934 | H73: 165.8 | I73: =H73/H72-1 -> -0.0042042042 | J73: 931.85 | K73: =J73/J72-1 -> 0.00037573806 | L73: 168.55 | M73: =L73/L72-1 -> 0.0035724918 | N73: 232.15 | O73: =N73/N72-1 -> -0.13198729
B74: 14-04-2024 | D74: 22147 | E74: =D74/D73-1 -> -0.012174425 | F74: 864.8 | G74: =F74/F73-1 -> -0.025302902 | H74: 162.1 | I74: =H74/H73-1 -> -0.022316043 | J74: 927.25 | K74: =J74/J73-1 -> -0.0049364168 | L74: 146.05 | M74: =L74/L73-1 -> -0.13349155 | N74: 222.75 | O74: =N74/N73-1 -> -0.040491062
B75: 45477 | D75: 22519.4 | E75: =D75/D74-1 -> 0.016814918 | F75: 866.45 | G75: =F75/F74-1 -> 0.0019079556 | H75: 163.5 | I75: =H75/H74-1 -> 0.008636644 | J75: 897.55 | K75: =J75/J74-1 -> -0.032030197 | L75: 155.35 | M75: =L75/L74-1 -> 0.063676823 | N75: 227.4 | O75: =N75/N74-1 -> 0.020875421
B76: 31-03-2024 | D76: 22513.7 | E76: =D76/D75-1 -> -0.00025311509 | F76: 857.1 | G76: =F76/F75-1 -> -0.010791159 | H76: 163.35 | I76: =H76/H75-1 -> -0.00091743119 | J76: 915.75 | K76: =J76/J75-1 -> 0.020277422 | L76: 146.2 | M76: =L76/L75-1 -> -0.05889926 | N76: 219.3 | O76: =N76/N75-1 -> -0.035620053
B77: 24-03-2024 | D77: 22326.9 | E77: =D77/D76-1 -> -0.0082971702 | F77: 830.2 | G77: =F77/F76-1 -> -0.031384903 | H77: 155.85 | I77: =H77/H76-1 -> -0.045913682 | J77: 849.15 | K77: =J77/J76-1 -> -0.072727273 | L77: 134.25 | M77: =L77/L76-1 -> -0.081737346 | N77: 202.85 | O77: =N77/N76-1 -> -0.0750114
B78: 17-03-2024 | D78: 22096.75 | E78: =D78/D77-1 -> -0.010308193 | F78: 824.8 | G78: =F78/F77-1 -> -0.0065044568 | H78: 151.8 | I78: =H78/H77-1 -> -0.025986526 | J78: 832.9 | K78: =J78/J77-1 -> -0.019136784 | L78: 130 | M78: =L78/L77-1 -> -0.031657356 | N78: 217.1 | O78: =N78/N77-1 -> 0.070248952
B79: 45568 | D79: 22023.35 | E79: =D79/D78-1 -> -0.0033217555 | F79: 780.65 | G79: =F79/F78-1 -> -0.053528128 | H79: 141.7 | I79: =H79/H78-1 -> -0.066534914 | J79: 767.75 | K79: =J79/J78-1 -> -0.078220675 | L79: 121.7 | M79: =L79/L78-1 -> -0.063846154 | N79: 199.95 | O79: =N79/N78-1 -> -0.078995854
B80: 45354 | D80: 22493.55 | E80: =D80/D79-1 -> 0.021350067 | F80: 830 | G80: =F80/F79-1 -> 0.06321655 | H80: 157.25 | I80: =H80/H79-1 -> 0.10973888 | J80: 839 | K80: =J80/J79-1 -> 0.092803647 | L80: 138.95 | M80: =L80/L79-1 -> 0.14174199 | N80: 208.7 | O80: =N80/N79-1 -> 0.04376094
B81: 25-02-2024 | D81: 22338.75 | E81: =D81/D80-1 -> -0.0068819728 | F81: 836.2 | G81: =F81/F80-1 -> 0.0074698795 | H81: 149.95 | I81: =H81/H80-1 -> -0.046422893 | J81: 822.85 | K81: =J81/J80-1 -> -0.019249106 | L81: 133 | M81: =L81/L80-1 -> -0.042821159 | N81: 215.7 | O81: =N81/N80-1 -> 0.033540968
B82: 18-02-2024 | D82: 22212.7 | E82: =D82/D81-1 -> -0.0056426613 | F82: 821 | G82: =F82/F81-1 -> -0.01817747 | H82: 145.45 | I82: =H82/H81-1 -> -0.030010003 | J82: 786.55 | K82: =J82/J81-1 -> -0.044114966 | L82: 128 | M82: =L82/L81-1 -> -0.037593985 | N82: 214.25 | O82: =N82/N81-1 -> -0.0067222995
B83: 45598 | D83: 22040.7 | E83: =D83/D82-1 -> -0.007743318 | F83: 819.95 | G83: =F83/F82-1 -> -0.0012789281 | H83: 142.3 | I83: =H83/H82-1 -> -0.021656927 | J83: 769.5 | K83: =J83/J82-1 -> -0.021676944 | L83: 127.45 | M83: =L83/L82-1 -> -0.004296875 | N83: 228.55 | O83: =N83/N82-1 -> 0.066744457
B84: 45384 | D84: 21782.5 | E84: =D84/D83-1 -> -0.011714691 | F84: 811.75 | G84: =F84/F83-1 -> -0.01000061 | H84: 141.3 | I84: =H84/H83-1 -> -0.0070274069 | J84: 761.45 | K84: =J84/J83-1 -> -0.010461339 | L84: 133.65 | M84: =L84/L83-1 -> 0.048646528 | N84: 220.65 | O84: =N84/N83-1 -> -0.034565741
B85: 28-01-2024 | D85: 21853.8 | E85: =D85/D84-1 -> 0.0032732698 | F85: 823.55 | G85: =F85/F84-1 -> 0.014536495 | H85: 138.7 | I85: =H85/H84-1 -> -0.018400566 | J85: 776 | K85: =J85/J84-1 -> 0.01910828 | L85: 128.3 | M85: =L85/L84-1 -> -0.040029929 | N85: 247.3 | O85: =N85/N84-1 -> 0.12077952
B86: 21-01-2024 | D86: 21352.6 | E86: =D86/D85-1 -> -0.022934227 | F86: 815.7 | G86: =F86/F85-1 -> -0.0095319046 | H86: 133.75 | I86: =H86/H85-1 -> -0.035688536 | J86: 716.3 | K86: =J86/J85-1 -> -0.07693299 | L86: 119.1 | M86: =L86/L85-1 -> -0.071706937 | N86: 231.75 | O86: =N86/N85-1 -> -0.062879094
B87: 14-01-2024 | D87: 21622.4 | E87: =D87/D86-1 -> 0.012635464 | F87: 816.65 | G87: =F87/F86-1 -> 0.0011646439 | H87: 134.25 | I87: =H87/H86-1 -> 0.0037383178 | J87: 729.25 | K87: =J87/J86-1 -> 0.018079017 | L87: 114.1 | M87: =L87/L86-1 -> -0.041981528 | N87: 255.85 | O87: =N87/N86-1 -> 0.10399137
B88: 45474 | D88: 21894.55 | E88: =D88/D87-1 -> 0.012586484 | F88: 825.8 | G88: =F88/F87-1 -> 0.01120431 | H88: 135.3 | I88: =H88/H87-1 -> 0.0078212291 | J88: 735.9 | K88: =J88/J87-1 -> 0.0091189578 | L88: 114.9 | M88: =L88/L87-1 -> 0.0070113935 | N88: 247.45 | O88: =N88/N87-1 -> -0.032831737
B89: 31-12-2023 | D89: 21710.8 | E89: =D89/D88-1 -> -0.0083924995 | F89: 829.4 | G89: =F89/F88-1 -> 0.0043594091 | H89: 133.65 | I89: =H89/H88-1 -> -0.012195122 | J89: 735.75 | K89: =J89/J88-1 -> -0.00020383204 | L89: 116.95 | M89: =L89/L88-1 -> 0.017841601 | N89: 251.15 | O89: =N89/N88-1 -> 0.014952516
B90: 24-12-2023 | D90: 21731.4 | E90: =D90/D89-1 -> 0.00094883652 | F90: 880.25 | G90: =F90/F89-1 -> 0.06130938 | H90: 139.6 | I90: =H90/H89-1 -> 0.044519267 | J90: 748.1 | K90: =J90/J89-1 -> 0.016785593 | L90: 123.65 | M90: =L90/L89-1 -> 0.05728944 | N90: 253.25 | O90: =N90/N89-1 -> 0.0083615369
B91: 17-12-2023 | D91: 21349.4 | E91: =D91/D90-1 -> -0.017578251 | F91: 855.3 | G91: =F91/F90-1 -> -0.02834422 | H91: 133.55 | I91: =H91/H90-1 -> -0.043338109 | J91: 726.4 | K91: =J91/J90-1 -> -0.029006817 | L91: 112.75 | M91: =L91/L90-1 -> -0.088152042 | N91: 250.5 | O91: =N91/N90-1 -> -0.010858835
B92: 45211 | D92: 21456.65 | E92: =D92/D91-1 -> 0.0050235604 | F92: 867.2 | G92: =F92/F91-1 -> 0.013913247 | H92: 136.45 | I92: =H92/H91-1 -> 0.021714714 | J92: 724.4 | K92: =J92/J91-1 -> -0.002753304 | L92: 111.45 | M92: =L92/L91-1 -> -0.011529933 | N92: 259.85 | O92: =N92/N91-1 -> 0.037325349
B93: 44997 | D93: 20969.4 | E93: =D93/D92-1 -> -0.022708578 | F93: 839.35 | G93: =F93/F92-1 -> -0.032114852 | H93: 129.2 | I93: =H93/H92-1 -> -0.053133016 | J93: 686.25 | K93: =J93/J92-1 -> -0.052664274 | L93: 98.1 | M93: =L93/L92-1 -> -0.11978466 | N93: 249.45 | O93: =N93/N92-1 -> -0.04002309
B94: 26-11-2023 | D94: 20267.9 | E94: =D94/D93-1 -> -0.033453508 | F94: 810.8 | G94: =F94/F93-1 -> -0.034014416 | H94: 130 | I94: =H94/H93-1 -> 0.0061919505 | J94: 692.2 | K94: =J94/J93-1 -> 0.0086703097 | L94: 93.15 | M94: =L94/L93-1 -> -0.050458716 | N94: 244.35 | O94: =N94/N93-1 -> -0.020444979
B95: 19-11-2023 | D95: 19794.7 | E95: =D95/D94-1 -> -0.023347263 | F95: 782.05 | G95: =F95/F94-1 -> -0.035458806 | H95: 125.95 | I95: =H95/H94-1 -> -0.031153846 | J95: 660.3 | K95: =J95/J94-1 -> -0.046084947 | L95: 89.2 | M95: =L95/L94-1 -> -0.042404724 | N95: 235.25 | O95: =N95/N94-1 -> -0.037241662
B96: 45271 | D96: 19731.8 | E96: =D96/D95-1 -> -0.0031776183 | F96: 768.8 | G96: =F96/F95-1 -> -0.016942651 | H96: 125.2 | I96: =H96/H95-1 -> -0.0059547439 | J96: 647.1 | K96: =J96/J95-1 -> -0.019990913 | L96: 89.3 | M96: =L96/L95-1 -> 0.0011210762 | N96: 233.3 | O96: =N96/N95-1 -> -0.0082890542
B97: 45057 | D97: 19425.35 | E97: =D97/D96-1 -> -0.015530768 | F97: 754.75 | G97: =F97/F96-1 -> -0.018275234 | H97: 120.05 | I97: =H97/H96-1 -> -0.041134185 | J97: 636.9 | K97: =J97/J96-1 -> -0.015762633 | L97: 88.1 | M97: =L97/L96-1 -> -0.01343785 | N97: 215.5 | O97: =N97/N96-1 -> -0.076296614
B98: 29-10-2023 | D98: 19230.6 | E98: =D98/D97-1 -> -0.010025559 | F98: 746.05 | G98: =F98/F97-1 -> -0.011526996 | H98: 117.3 | I98: =H98/H97-1 -> -0.022907122 | J98: 596.9 | K98: =J98/J97-1 -> -0.062804208 | L98: 84.9 | M98: =L98/L97-1 -> -0.036322361 | N98: 215.65 | O98: =N98/N97-1 -> 0.00069605568
B99: 22-10-2023 | D99: 19047.25 | E99: =D99/D98-1 -> -0.0095342839 | F99: 732 | G99: =F99/F98-1 -> -0.018832518 | H99: 119.9 | I99: =H99/H98-1 -> 0.022165388 | J99: 643.9 | K99: =J99/J98-1 -> 0.078740157 | L99: 83.95 | M99: =L99/L98-1 -> -0.011189635 | N99: 214.15 | O99: =N99/N98-1 -> -0.0069557153
B100: 15-10-2023 | D100: 19542.65 | E100: =D100/D99-1 -> 0.026009004 | F100: 769.4 | G100: =F100/F99-1 -> 0.051092896 | H100: 123.1 | I100: =H100/H99-1 -> 0.026688907 | J100: 662.4 | K100: =J100/J99-1 -> 0.028731169 | L100: 86.9 | M100: =L100/L99-1 -> 0.035139964 | N100: 216.6 | O100: =N100/N99-1 -> 0.011440579
B101: 45148 | D101: 19751.05 | E101: =D101/D100-1 -> 0.010663856 | F101: 777.25 | G101: =F101/F100-1 -> 0.010202755 | H101: 125.05 | I101: =H101/H100-1 -> 0.01584078 | J101: 681.5 | K101: =J101/J100-1 -> 0.028834541 | L101: 88.9 | M101: =L101/L100-1 -> 0.02301496 | N101: 215.4 | O101: =N101/N100-1 -> -0.0055401662
B102: 44936 | D102: 19653.5 | E102: =D102/D101-1 -> -0.0049389779 | F102: 765.2 | G102: =F102/F101-1 -> -0.015503377 | H102: 125.9 | I102: =H102/H101-1 -> 0.0067972811 | J102: 683.45 | K102: =J102/J101-1 -> 0.0028613353 | L102: 88.85 | M102: =L102/L101-1 -> -0.0005624297 | N102: 215.95 | O102: =N102/N101-1 -> 0.002553389
B103: 24-09-2023 | D103: 19638.3 | E103: =D103/D102-1 -> -0.00077339914 | F103: 779.6 | G103: =F103/F102-1 -> 0.01881861 | H103: 128.9 | I103: =H103/H102-1 -> 0.023828435 | J103: 701.35 | K103: =J103/J102-1 -> 0.02619065 | L103: 93.85 | M103: =L103/L102-1 -> 0.05627462 | N103: 220.3 | O103: =N103/N102-1 -> 0.020143552
...

Sheet WACC input data
B1: Other Input Calculations
B3: Cost of equity Inputs
B4: 10 Year Govt. bond Yeild ( India ) | C4: 0.06188
B5: India country default spread | C5: 0.0218
B6: Mature market Base premium ( US ) | C6: 0.0433
B7: Equity risk premium ( India) | C7: 0.0726
B9: Cost of Debt Inputs
B10: Risk- free rate | C10: =C4-C5 -> 0.04008
B11: Country Risk Premium | C11: 0.0293
B12: Company default spread | C12: 0.006
